cross_aws_account_iam_role/__init__.py
cross_aws_account_iam_role/_version.py
cross_aws_account_iam_role/api.py
cross_aws_account_iam_role/impl.py
cross_aws_account_iam_role/paths.py
cross_aws_account_iam_role/docs/__init__.py
cross_aws_account_iam_role/tests/__init__.py
cross_aws_account_iam_role/tests/helper.py
cross_aws_account_iam_role/vendor/__init__.py
cross_aws_account_iam_role/vendor/pytest_cov_helper.py
cross_aws_account_iam_role-0.1.2.dist-info/AUTHORS.rst
cross_aws_account_iam_role-0.1.2.dist-info/LICENSE.txt
cross_aws_account_iam_role-0.1.2.dist-info/METADATA
cross_aws_account_iam_role-0.1.2.dist-info/WHEEL
cross_aws_account_iam_role-0.1.2.dist-info/top_level.txt
cross_aws_account_iam_role-0.1.2.dist-info/RECORD
